catalyst_orm/__init__.py
catalyst_orm/columns.py
catalyst_orm/conditions.py
catalyst_orm/connection_interface.py
catalyst_orm/py.typed
catalyst_orm/query_builder.py
catalyst_orm/relationships.py
catalyst_orm/postgres/__init__.py
catalyst_orm/postgres/column_types.py
catalyst_orm/postgres/tables.py
catalyst_orm-0.0.1a2.dist-info/METADATA
catalyst_orm-0.0.1a2.dist-info/WHEEL
catalyst_orm-0.0.1a2.dist-info/top_level.txt
catalyst_orm-0.0.1a2.dist-info/RECORD
