Metadata-Version: 2.4
Name: catalyst-orm
Version: 0.0.1a2
Summary: catalyst is a typesafe python query builder
Author-email: Karol Broda <me@karolbroda.com>
Requires-Python: >=3.10
